unity_sps_ogc_processes_api_python_client/__init__.py
unity_sps_ogc_processes_api_python_client/api_client.py
unity_sps_ogc_processes_api_python_client/api_response.py
unity_sps_ogc_processes_api_python_client/configuration.py
unity_sps_ogc_processes_api_python_client/exceptions.py
unity_sps_ogc_processes_api_python_client/py.typed
unity_sps_ogc_processes_api_python_client/rest.py
unity_sps_ogc_processes_api_python_client/api/__init__.py
unity_sps_ogc_processes_api_python_client/api/api_api.py
unity_sps_ogc_processes_api_python_client/api/conformance_api.py
unity_sps_ogc_processes_api_python_client/api/default_api.py
unity_sps_ogc_processes_api_python_client/api/dru_api.py
unity_sps_ogc_processes_api_python_client/api/health_api.py
unity_sps_ogc_processes_api_python_client/api/jobs_api.py
unity_sps_ogc_processes_api_python_client/api/landing_page_api.py
unity_sps_ogc_processes_api_python_client/api/processes_api.py
unity_sps_ogc_processes_api_python_client/models/__init__.py
unity_sps_ogc_processes_api_python_client/models/actual_instance.py
unity_sps_ogc_processes_api_python_client/models/actual_instance1.py
unity_sps_ogc_processes_api_python_client/models/actual_instance2.py
unity_sps_ogc_processes_api_python_client/models/actual_instance3.py
unity_sps_ogc_processes_api_python_client/models/actual_instance4.py
unity_sps_ogc_processes_api_python_client/models/actual_instance5.py
unity_sps_ogc_processes_api_python_client/models/actual_instance6.py
unity_sps_ogc_processes_api_python_client/models/bbox.py
unity_sps_ogc_processes_api_python_client/models/bbox1.py
unity_sps_ogc_processes_api_python_client/models/bbox_bbox_inner.py
unity_sps_ogc_processes_api_python_client/models/bbox_def_crs.py
unity_sps_ogc_processes_api_python_client/models/conf_classes.py
unity_sps_ogc_processes_api_python_client/models/cpumax.py
unity_sps_ogc_processes_api_python_client/models/cpumin.py
unity_sps_ogc_processes_api_python_client/models/crs.py
unity_sps_ogc_processes_api_python_client-2.0.1.dist-info/LICENSE
unity_sps_ogc_processes_api_python_client-2.0.1.dist-info/METADATA
unity_sps_ogc_processes_api_python_client-2.0.1.dist-info/WHEEL
unity_sps_ogc_processes_api_python_client-2.0.1.dist-info/top_level.txt
unity_sps_ogc_processes_api_python_client-2.0.1.dist-info/RECORD
